mkdocs_obsidian_bridge_plugin/__init__.py
mkdocs_obsidian_bridge_plugin/plugin.py
mkdocs_obsidian_bridge_plugin-1.0.0.dist-info/LICENSE
mkdocs_obsidian_bridge_plugin-1.0.0.dist-info/WHEEL
mkdocs_obsidian_bridge_plugin-1.0.0.dist-info/entry_points.txt
mkdocs_obsidian_bridge_plugin-1.0.0.dist-info/METADATA
mkdocs_obsidian_bridge_plugin-1.0.0.dist-info/RECORD
