Metadata-Version: 2.1
Name: mkdocs-obsidian-bridge-plugin
Version: 1.0.0
Summary: An MkDocs plugin that helps exporting your Obsidian vault as an MkDocs site.
License: BSD-3-Clause
Author: GooRoo
Author-email: sergey.olendarenko@gmail.com
Requires-Python: >=3.10,<4.0
Classifier: License :: OSI Approved :: BSD License
Classifier: Programming Language :: Python :: 3
Classifier: Programming Language :: Python :: 3.10
Classifier: Programming Language :: Python :: 3.11
Requires-Dist: markdown (>=3.2.1,<3.4)
Requires-Dist: mkdocs (>=1.4.2,<2.0.0)
